Metadata-Version: 2.1
Name: jasmine-sis
Version: 0.1.0.0.8
Summary: JASMINE: Joint Analysis of Simulations for Microlensing INterest Events
Home-page: https://github.com/stelais/jasmine
Author: Stela IS
Author-email: stela.ishitanisilva@nasa.gov
License: MIT
License-File: LICENSE
Requires-Dist: pandas==2.1.4
Requires-Dist: jupyter==1.0.0
Requires-Dist: notebook==7.1.3
Requires-Dist: ipykernel==6.29.4
Requires-Dist: matplotlib==3.8.4
Requires-Dist: astropy==6.1.0
Requires-Dist: jplephem==2.22
